Workbook

Sheet Instructions
A1: HOA Quarterly Billing System
A2: Focused Excel billing database for efficient quarterly HOA or condo assessment billing.
A4: Purpose
A5: This workbook is designed for one practical task: producing, tracking, and reviewing quarterly HOA billing more efficiently.
A7: Recommended quarterly workflow
A8: 1. Update Setup for the year, quarter, billing date, due date, and memo. 2. Update Units_Owners. 3. Review Quarterly_Billing_Run. 4. Use Invoice_Template to print/save invoices. 5. Enter payments in Payments. 6. Review Aging_Report and Ledger.
A10: Macro strategy
A11: This file is macro-free for review and safe opening. The Macro_Blueprint sheet lists the automation I recommend after you approve the layout: generate billing, export PDFs, mark invoices sent, apply late fees, and create statements.
A13: Important
A14: Rows marked SAMPLE are for review only. Replace or delete them before live billing. Review all formulas, amounts, late-fee rules, and collection practices against your HOA documents.
A18: Primary sheets
A19: Setup | B19: Billing cycle control panel.
A20: Units_Owners | B20: Billing directory and quarterly dues by unit.
A21: Quarterly_Billing_Run | B21: Invoice rows generated from unit records.
A22: Payments | B22: Payment entry and reference tracking.
A23: Ledger | B23: Manual audit ledger for charges, payments, credits, and adjustments.
A24: Invoice_Template | B24: Printable invoice view selected by invoice number.
A25: Aging_Report | B25: Open balance and days-past-due review.
A26: Macro_Blueprint | B26: Recommended automation for a later .xlsm version.

Sheet Setup
A1: Billing Setup
A4: Association Name | B4: Example HOA / Condominium Association
A5: Billing Year | B5: 2026
A6: Quarter | B6: Q1
A7: Billing Date | B7: 1/1/2026
A8: Due Date | B8: 1/31/2026
A9: Late Fee Date | B9: 2/1/2026
A10: Standard Quarterly Dues | B10: 350
A11: Default Special Assessment | B11: 0
A12: Late Fee Amount | B12: 25
A13: Payment Instructions | B13: Pay by check, ACH, or approved online payment method.
A14: Invoice Memo | B14: Quarterly assessment invoice. Please pay by the due date to avoid late fees.
A15: Next Invoice Sequence | B15: 1

Sheet Lookups
A1: Dropdown Values
A4: Quarter | B4: Billing Preference | C4: Yes/No | D4: Invoice Status | E4: Payment Method | F4: Receipt Sent | G4: Ledger Type | H4: Delivery Status
A5: Q1 | B5: Email | C5: Yes | D5: Draft | E5: ACH | F5: Yes | G5: Charge | H5: Not Sent
A6: Q2 | B6: Mail | C6: No | D6: Open | E6: Check | F6: No | G6: Payment | H6: Sent
A7: Q3 | B7: Both | D7: Sent | E7: Credit Card | F7: N/A | G7: Adjustment | H7: Delivered
A8: Q4 | B8: Do Not Bill | D8: Paid | E8: Debit Card | G8: Late Fee | H8: Bounced
D9: Past Due | E9: Cash | G9: Credit | H9: Returned
D10: Skip - Inactive | E10: Money Order | G10: Write-Off | H10: Printed
D11: Void | E11: Wire | H11: Mailed
E12: Other

Sheet Units_Owners
A1: Units and Owners
A4: Unit ID | B4: Condo/Unit No. | C4: Owner Name | D4: Billing Email | E4: Phone | F4: Mailing Address | G4: Billing Preference | H4: Quarterly Dues | I4: Active? | J4: Prior Balance Override | K4: Notes
A5: U-001 | B5: 101 | C5: SAMPLE Owner One | D5: owner1@example.com | E5: 555-0101 | F5: 101 Main St | G5: Email | H5: 350 | I5: Yes | J5: 0 | K5: Replace sample row
A6: U-002 | B6: 102 | C6: SAMPLE Owner Two | D6: owner2@example.com | E6: 555-0102 | F6: 102 Main St | G6: Mail | H6: 350 | I6: Yes | J6: 0 | K6: Replace sample row
A7: U-003 | B7: 103 | C7: SAMPLE Owner Three | D7: owner3@example.com | E7: 555-0103 | F7: 103 Main St | G7: Both | H7: 350 | I7: Yes | J7: 45 | K7: Prior balance example
H8: =Setup!$B$10 | I8: Yes | J8: 0
H9: =Setup!$B$10 | I9: Yes | J9: 0
H10: =Setup!$B$10 | I10: Yes | J10: 0
H11: =Setup!$B$10 | I11: Yes | J11: 0
H12: =Setup!$B$10 | I12: Yes | J12: 0
H13: =Setup!$B$10 | I13: Yes | J13: 0
H14: =Setup!$B$10 | I14: Yes | J14: 0
H15: =Setup!$B$10 | I15: Yes | J15: 0
H16: =Setup!$B$10 | I16: Yes | J16: 0
H17: =Setup!$B$10 | I17: Yes | J17: 0
H18: =Setup!$B$10 | I18: Yes | J18: 0
H19: =Setup!$B$10 | I19: Yes | J19: 0
... H504: =Setup!$B$10 | I504: Yes | J504: 0

Sheet Quarterly_Billing_Run
A1: Quarterly Billing Run
A4: Invoice No. | B4: Billing Year | C4: Quarter | D4: Unit ID | E4: Condo/Unit No. | F4: Owner Name | G4: Billing Email | H4: Charge Date | I4: Due Date | J4: Prior Balance | K4: Quarterly Dues | L4: Special Assessment | M4: Late Fee | N4: Total Due | O4: Payments Applied | P4: Balance Due | Q4: Status | R4: Sent Date | S4: Notes
A5: =IF($D5="","","INV-"&$B5&"-"&$C5&"-"&TEXT(ROW(A1),"0000")) | B5: =Setup!$B$5 | C5: =Setup!$B$6 | D5: =IFERROR(INDEX(Units_Owners!$A$5:$A$504,ROWS($A$5:A5)),"") | E5: =IF($D5="","",IFERROR(INDEX(Units_Owners!$B$5:$B$504,MATCH($D5,Units_Owners!$A$5:$A$504,0)),"")) | F5: =IF($D5="","",IFERROR(INDEX(Units_Owners!$C$5:$C$504,MATCH($D5,Units_Owners!$A$5:$A$504,0)),"")) | G5: =IF($D5="","",IFERROR(INDEX(Units_Owners!$D$5:$D$504,MATCH($D5,Units_Owners!$A$5:$A$504,0)),"")) | H5: =Setup!$B$7 | I5: =Setup!$B$8 | J5: =IF($D5="","",IFERROR(INDEX(Units_Owners!$J$5:$J$504,MATCH($D5,Units_Owners!$A$5:$A$504,0)),0)+SUMIFS(Ledger!$F:$F,Ledger!$B:$B,$D5,Ledger!$D:$D,"<"&$H5)-SUMIFS(Ledger!$G:$G,Ledger!$B:$B,$D5,Ledger!$D:$D,"<"&$H5)) | K5: =IF($D5="","",IFERROR(INDEX(Units_Owners!$H$5:$H$504,MATCH($D5,Units_Owners!$A$5:$A$504,0)),Setup!$B$10)) | L5: =IF($D5="","",Setup!$B$11) | M5: =IF($D5="","",IF(AND(TODAY()>=Setup!$B$9,$P5>0),Setup!$B$12,0)) | N5: =IF($D5="","",SUM($J5:$M5)) | O5: =IF($A5="","",SUMIFS(Payments!$F:$F,Payments!$D:$D,$A5)) | P5: =IF($D5="","",MAX(0,$N5-$O5)) | Q5: =IF($D5="","",IF(IFERROR(INDEX(Units_Owners!$I$5:$I$504,MATCH($D5,Units_Owners!$A$5:$A$504,0)),"No")<>"Yes","Skip - Inactive",IF($P5=0,"Paid",IF(TODAY()>$I5,"Past Due","Open"))))
A6: =IF($D6="","","INV-"&$B6&"-"&$C6&"-"&TEXT(ROW(A2),"0000")) | B6: =Setup!$B$5 | C6: =Setup!$B$6 | D6: =IFERROR(INDEX(Units_Owners!$A$5:$A$504,ROWS($A$5:A6)),"") | E6: =IF($D6="","",IFERROR(INDEX(Units_Owners!$B$5:$B$504,MATCH($D6,Units_Owners!$A$5:$A$504,0)),"")) | F6: =IF($D6="","",IFERROR(INDEX(Units_Owners!$C$5:$C$504,MATCH($D6,Units_Owners!$A$5:$A$504,0)),"")) | G6: =IF($D6="","",IFERROR(INDEX(Units_Owners!$D$5:$D$504,MATCH($D6,Units_Owners!$A$5:$A$504,0)),"")) | H6: =Setup!$B$7 | I6: =Setup!$B$8 | J6: =IF($D6="","",IFERROR(INDEX(Units_Owners!$J$5:$J$504,MATCH($D6,Units_Owners!$A$5:$A$504,0)),0)+SUMIFS(Ledger!$F:$F,Ledger!$B:$B,$D6,Ledger!$D:$D,"<"&$H6)-SUMIFS(Ledger!$G:$G,Ledger!$B:$B,$D6,Ledger!$D:$D,"<"&$H6)) | K6: =IF($D6="","",IFERROR(INDEX(Units_Owners!$H$5:$H$504,MATCH($D6,Units_Owners!$A$5:$A$504,0)),Setup!$B$10)) | L6: =IF($D6="","",Setup!$B$11) | M6: =IF($D6="","",IF(AND(TODAY()>=Setup!$B$9,$P6>0),Setup!$B$12,0)) | N6: =IF($D6="","",SUM($J6:$M6)) | O6: =IF($A6="","",SUMIFS(Payments!$F:$F,Payments!$D:$D,$A6)) | P6: =IF($D6="","",MAX(0,$N6-$O6)) | Q6: =IF($D6="","",IF(IFERROR(INDEX(Units_Owners!$I$5:$I$504,MATCH($D6,Units_Owners!$A$5:$A$504,0)),"No")<>"Yes","Skip - Inactive",IF($P6=0,"Paid",IF(TODAY()>$I6,"Past Due","Open"))))
A7: =IF($D7="","","INV-"&$B7&"-"&$C7&"-"&TEXT(ROW(A3),"0000")) | B7: =Setup!$B$5 | C7: =Setup!$B$6 | D7: =IFERROR(INDEX(Units_Owners!$A$5:$A$504,ROWS($A$5:A7)),"") | E7: =IF($D7="","",IFERROR(INDEX(Units_Owners!$B$5:$B$504,MATCH($D7,Units_Owners!$A$5:$A$504,0)),"")) | F7: =IF($D7="","",IFERROR(INDEX(Units_Owners!$C$5:$C$504,MATCH($D7,Units_Owners!$A$5:$A$504,0)),"")) | G7: =IF($D7="","",IFERROR(INDEX(Units_Owners!$D$5:$D$504,MATCH($D7,Units_Owners!$A$5:$A$504,0)),"")) | H7: =Setup!$B$7 | I7: =Setup!$B$8 | J7: =IF($D7="","",IFERROR(INDEX(Units_Owners!$J$5:$J$504,MATCH($D7,Units_Owners!$A$5:$A$504,0)),0)+SUMIFS(Ledger!$F:$F,Ledger!$B:$B,$D7,Ledger!$D:$D,"<"&$H7)-SUMIFS(Ledger!$G:$G,Ledger!$B:$B,$D7,Ledger!$D:$D,"<"&$H7)) | K7: =IF($D7="","",IFERROR(INDEX(Units_Owners!$H$5:$H$504,MATCH($D7,Units_Owners!$A$5:$A$504,0)),Setup!$B$10)) | L7: =IF($D7="","",Setup!$B$11) | M7: =IF($D7="","",IF(AND(TODAY()>=Setup!$B$9,$P7>0),Setup!$B$12,0)) | N7: =IF($D7="","",SUM($J7:$M7)) | O7: =IF($A7="","",SUMIFS(Payments!$F:$F,Payments!$D:$D,$A7)) | P7: =IF($D7="","",MAX(0,$N7-$O7)) | Q7: =IF($D7="","",IF(IFERROR(INDEX(Units_Owners!$I$5:$I$504,MATCH($D7,Units_Owners!$A$5:$A$504,0)),"No")<>"Yes","Skip - Inactive",IF($P7=0,"Paid",IF(TODAY()>$I7,"Past Due","Open"))))
A8: =IF($D8="","","INV-"&$B8&"-"&$C8&"-"&TEXT(ROW(A4),"0000")) | B8: =Setup!$B$5 | C8: =Setup!$B$6 | D8: =IFERROR(INDEX(Units_Owners!$A$5:$A$504,ROWS($A$5:A8)),"") | E8: =IF($D8="","",IFERROR(INDEX(Units_Owners!$B$5:$B$504,MATCH($D8,Units_Owners!$A$5:$A$504,0)),"")) | F8: =IF($D8="","",IFERROR(INDEX(Units_Owners!$C$5:$C$504,MATCH($D8,Units_Owners!$A$5:$A$504,0)),"")) | G8: =IF($D8="","",IFERROR(INDEX(Units_Owners!$D$5:$D$504,MATCH($D8,Units_Owners!$A$5:$A$504,0)),"")) | H8: =Setup!$B$7 | I8: =Setup!$B$8 | J8: =IF($D8="","",IFERROR(INDEX(Units_Owners!$J$5:$J$504,MATCH($D8,Units_Owners!$A$5:$A$504,0)),0)+SUMIFS(Ledger!$F:$F,Ledger!$B:$B,$D8,Ledger!$D:$D,"<"&$H8)-SUMIFS(Ledger!$G:$G,Ledger!$B:$B,$D8,Ledger!$D:$D,"<"&$H8)) | K8: =IF($D8="","",IFERROR(INDEX(Units_Owners!$H$5:$H$504,MATCH($D8,Units_Owners!$A$5:$A$504,0)),Setup!$B$10)) | L8: =IF($D8="","",Setup!$B$11) | M8: =IF($D8="","",IF(AND(TODAY()>=Setup!$B$9,$P8>0),Setup!$B$12,0)) | N8: =IF($D8="","",SUM($J8:$M8)) | O8: =IF($A8="","",SUMIFS(Payments!$F:$F,Payments!$D:$D,$A8)) | P8: =IF($D8="","",MAX(0,$N8-$O8)) | Q8: =IF($D8="","",IF(IFERROR(INDEX(Units_Owners!$I$5:$I$504,MATCH($D8,Units_Owners!$A$5:$A$504,0)),"No")<>"Yes","Skip - Inactive",IF($P8=0,"Paid",IF(TODAY()>$I8,"Past Due","Open"))))
A9: =IF($D9="","","INV-"&$B9&"-"&$C9&"-"&TEXT(ROW(A5),"0000")) | B9: =Setup!$B$5 | C9: =Setup!$B$6 | D9: =IFERROR(INDEX(Units_Owners!$A$5:$A$504,ROWS($A$5:A9)),"") | E9: =IF($D9="","",IFERROR(INDEX(Units_Owners!$B$5:$B$504,MATCH($D9,Units_Owners!$A$5:$A$504,0)),"")) | F9: =IF($D9="","",IFERROR(INDEX(Units_Owners!$C$5:$C$504,MATCH($D9,Units_Owners!$A$5:$A$504,0)),"")) | G9: =IF($D9="","",IFERROR(INDEX(Units_Owners!$D$5:$D$504,MATCH($D9,Units_Owners!$A$5:$A$504,0)),"")) | H9: =Setup!$B$7 | I9: =Setup!$B$8 | J9: =IF($D9="","",IFERROR(INDEX(Units_Owners!$J$5:$J$504,MATCH($D9,Units_Owners!$A$5:$A$504,0)),0)+SUMIFS(Ledger!$F:$F,Ledger!$B:$B,$D9,Ledger!$D:$D,"<"&$H9)-SUMIFS(Ledger!$G:$G,Ledger!$B:$B,$D9,Ledger!$D:$D,"<"&$H9)) | K9: =IF($D9="","",IFERROR(INDEX(Units_Owners!$H$5:$H$504,MATCH($D9,Units_Owners!$A$5:$A$504,0)),Setup!$B$10)) | L9: =IF($D9="","",Setup!$B$11) | M9: =IF($D9="","",IF(AND(TODAY()>=Setup!$B$9,$P9>0),Setup!$B$12,0)) | N9: =IF($D9="","",SUM($J9:$M9)) | O9: =IF($A9="","",SUMIFS(Payments!$F:$F,Payments!$D:$D,$A9)) | P9: =IF($D9="","",MAX(0,$N9-$O9)) | Q9: =IF($D9="","",IF(IFERROR(INDEX(Units_Owners!$I$5:$I$504,MATCH($D9,Units_Owners!$A$5:$A$504,0)),"No")<>"Yes","Skip - Inactive",IF($P9=0,"Paid",IF(TODAY()>$I9,"Past Due","Open"))))
A10: =IF($D10="","","INV-"&$B10&"-"&$C10&"-"&TEXT(ROW(A6),"0000")) | B10: =Setup!$B$5 | C10: =Setup!$B$6 | D10: =IFERROR(INDEX(Units_Owners!$A$5:$A$504,ROWS($A$5:A10)),"") | E10: =IF($D10="","",IFERROR(INDEX(Units_Owners!$B$5:$B$504,MATCH($D10,Units_Owners!$A$5:$A$504,0)),"")) | F10: =IF($D10="","",IFERROR(INDEX(Units_Owners!$C$5:$C$504,MATCH($D10,Units_Owners!$A$5:$A$504,0)),"")) | G10: =IF($D10="","",IFERROR(INDEX(Units_Owners!$D$5:$D$504,MATCH($D10,Units_Owners!$A$5:$A$504,0)),"")) | H10: =Setup!$B$7 | I10: =Setup!$B$8 | J10: =IF($D10="","",IFERROR(INDEX(Units_Owners!$J$5:$J$504,MATCH($D10,Units_Owners!$A$5:$A$504,0)),0)+SUMIFS(Ledger!$F:$F,Ledger!$B:$B,$D10,Ledger!$D:$D,"<"&$H10)-SUMIFS(Ledger!$G:$G,Ledger!$B:$B,$D10,Ledger!$D:$D,"<"&$H10)) | K10: =IF($D10="","",IFERROR(INDEX(Units_Owners!$H$5:$H$504,MATCH($D10,Units_Owners!$A$5:$A$504,0)),Setup!$B$10)) | L10: =IF($D10="","",Setup!$B$11) | M10: =IF($D10="","",IF(AND(TODAY()>=Setup!$B$9,$P10>0),Setup!$B$12,0)) | N10: =IF($D10="","",SUM($J10:$M10)) | O10: =IF($A10="","",SUMIFS(Payments!$F:$F,Payments!$D:$D,$A10)) | P10: =IF($D10="","",MAX(0,$N10-$O10)) | Q10: =IF($D10="","",IF(IFERROR(INDEX(Units_Owners!$I$5:$I$504,MATCH($D10,Units_Owners!$A$5:$A$504,0)),"No")<>"Yes","Skip - Inactive",IF($P10=0,"Paid",IF(TODAY()>$I10,"Past Due","Open"))))
A11: =IF($D11="","","INV-"&$B11&"-"&$C11&"-"&TEXT(ROW(A7),"0000")) | B11: =Setup!$B$5 | C11: =Setup!$B$6 | D11: =IFERROR(INDEX(Units_Owners!$A$5:$A$504,ROWS($A$5:A11)),"") | E11: =IF($D11="","",IFERROR(INDEX(Units_Owners!$B$5:$B$504,MATCH($D11,Units_Owners!$A$5:$A$504,0)),"")) | F11: =IF($D11="","",IFERROR(INDEX(Units_Owners!$C$5:$C$504,MATCH($D11,Units_Owners!$A$5:$A$504,0)),"")) | G11: =IF($D11="","",IFERROR(INDEX(Units_Owners!$D$5:$D$504,MATCH($D11,Units_Owners!$A$5:$A$504,0)),"")) | H11: =Setup!$B$7 | I11: =Setup!$B$8 | J11: =IF($D11="","",IFERROR(INDEX(Units_Owners!$J$5:$J$504,MATCH($D11,Units_Owners!$A$5:$A$504,0)),0)+SUMIFS(Ledger!$F:$F,Ledger!$B:$B,$D11,Ledger!$D:$D,"<"&$H11)-SUMIFS(Ledger!$G:$G,Ledger!$B:$B,$D11,Ledger!$D:$D,"<"&$H11)) | K11: =IF($D11="","",IFERROR(INDEX(Units_Owners!$H$5:$H$504,MATCH($D11,Units_Owners!$A$5:$A$504,0)),Setup!$B$10)) | L11: =IF($D11="","",Setup!$B$11) | M11: =IF($D11="","",IF(AND(TODAY()>=Setup!$B$9,$P11>0),Setup!$B$12,0)) | N11: =IF($D11="","",SUM($J11:$M11)) | O11: =IF($A11="","",SUMIFS(Payments!$F:$F,Payments!$D:$D,$A11)) | P11: =IF($D11="","",MAX(0,$N11-$O11)) | Q11: =IF($D11="","",IF(IFERROR(INDEX(Units_Owners!$I$5:$I$504,MATCH($D11,Units_Owners!$A$5:$A$504,0)),"No")<>"Yes","Skip - Inactive",IF($P11=0,"Paid",IF(TODAY()>$I11,"Past Due","Open"))))
A12: =IF($D12="","","INV-"&$B12&"-"&$C12&"-"&TEXT(ROW(A8),"0000")) | B12: =Setup!$B$5 | C12: =Setup!$B$6 | D12: =IFERROR(INDEX(Units_Owners!$A$5:$A$504,ROWS($A$5:A12)),"") | E12: =IF($D12="","",IFERROR(INDEX(Units_Owners!$B$5:$B$504,MATCH($D12,Units_Owners!$A$5:$A$504,0)),"")) | F12: =IF($D12="","",IFERROR(INDEX(Units_Owners!$C$5:$C$504,MATCH($D12,Units_Owners!$A$5:$A$504,0)),"")) | G12: =IF($D12="","",IFERROR(INDEX(Units_Owners!$D$5:$D$504,MATCH($D12,Units_Owners!$A$5:$A$504,0)),"")) | H12: =Setup!$B$7 | I12: =Setup!$B$8 | J12: =IF($D12="","",IFERROR(INDEX(Units_Owners!$J$5:$J$504,MATCH($D12,Units_Owners!$A$5:$A$504,0)),0)+SUMIFS(Ledger!$F:$F,Ledger!$B:$B,$D12,Ledger!$D:$D,"<"&$H12)-SUMIFS(Ledger!$G:$G,Ledger!$B:$B,$D12,Ledger!$D:$D,"<"&$H12)) | K12: =IF($D12="","",IFERROR(INDEX(Units_Owners!$H$5:$H$504,MATCH($D12,Units_Owners!$A$5:$A$504,0)),Setup!$B$10)) | L12: =IF($D12="","",Setup!$B$11) | M12: =IF($D12="","",IF(AND(TODAY()>=Setup!$B$9,$P12>0),Setup!$B$12,0)) | N12: =IF($D12="","",SUM($J12:$M12)) | O12: =IF($A12="","",SUMIFS(Payments!$F:$F,Payments!$D:$D,$A12)) | P12: =IF($D12="","",MAX(0,$N12-$O12)) | Q12: =IF($D12="","",IF(IFERROR(INDEX(Units_Owners!$I$5:$I$504,MATCH($D12,Units_Owners!$A$5:$A$504,0)),"No")<>"Yes","Skip - Inactive",IF($P12=0,"Paid",IF(TODAY()>$I12,"Past Due","Open"))))
A13: =IF($D13="","","INV-"&$B13&"-"&$C13&"-"&TEXT(ROW(A9),"0000")) | B13: =Setup!$B$5 | C13: =Setup!$B$6 | D13: =IFERROR(INDEX(Units_Owners!$A$5:$A$504,ROWS($A$5:A13)),"") | E13: =IF($D13="","",IFERROR(INDEX(Units_Owners!$B$5:$B$504,MATCH($D13,Units_Owners!$A$5:$A$504,0)),"")) | F13: =IF($D13="","",IFERROR(INDEX(Units_Owners!$C$5:$C$504,MATCH($D13,Units_Owners!$A$5:$A$504,0)),"")) | G13: =IF($D13="","",IFERROR(INDEX(Units_Owners!$D$5:$D$504,MATCH($D13,Units_Owners!$A$5:$A$504,0)),"")) | H13: =Setup!$B$7 | I13: =Setup!$B$8 | J13: =IF($D13="","",IFERROR(INDEX(Units_Owners!$J$5:$J$504,MATCH($D13,Units_Owners!$A$5:$A$504,0)),0)+SUMIFS(Ledger!$F:$F,Ledger!$B:$B,$D13,Ledger!$D:$D,"<"&$H13)-SUMIFS(Ledger!$G:$G,Ledger!$B:$B,$D13,Ledger!$D:$D,"<"&$H13)) | K13: =IF($D13="","",IFERROR(INDEX(Units_Owners!$H$5:$H$504,MATCH($D13,Units_Owners!$A$5:$A$504,0)),Setup!$B$10)) | L13: =IF($D13="","",Setup!$B$11) | M13: =IF($D13="","",IF(AND(TODAY()>=Setup!$B$9,$P13>0),Setup!$B$12,0)) | N13: =IF($D13="","",SUM($J13:$M13)) | O13: =IF($A13="","",SUMIFS(Payments!$F:$F,Payments!$D:$D,$A13)) | P13: =IF($D13="","",MAX(0,$N13-$O13)) | Q13: =IF($D13="","",IF(IFERROR(INDEX(Units_Owners!$I$5:$I$504,MATCH($D13,Units_Owners!$A$5:$A$504,0)),"No")<>"Yes","Skip - Inactive",IF($P13=0,"Paid",IF(TODAY()>$I13,"Past Due","Open"))))
A14: =IF($D14="","","INV-"&$B14&"-"&$C14&"-"&TEXT(ROW(A10),"0000")) | B14: =Setup!$B$5 | C14: =Setup!$B$6 | D14: =IFERROR(INDEX(Units_Owners!$A$5:$A$504,ROWS($A$5:A14)),"") | E14: =IF($D14="","",IFERROR(INDEX(Units_Owners!$B$5:$B$504,MATCH($D14,Units_Owners!$A$5:$A$504,0)),"")) | F14: =IF($D14="","",IFERROR(INDEX(Units_Owners!$C$5:$C$504,MATCH($D14,Units_Owners!$A$5:$A$504,0)),"")) | G14: =IF($D14="","",IFERROR(INDEX(Units_Owners!$D$5:$D$504,MATCH($D14,Units_Owners!$A$5:$A$504,0)),"")) | H14: =Setup!$B$7 | I14: =Setup!$B$8 | J14: =IF($D14="","",IFERROR(INDEX(Units_Owners!$J$5:$J$504,MATCH($D14,Units_Owners!$A$5:$A$504,0)),0)+SUMIFS(Ledger!$F:$F,Ledger!$B:$B,$D14,Ledger!$D:$D,"<"&$H14)-SUMIFS(Ledger!$G:$G,Ledger!$B:$B,$D14,Ledger!$D:$D,"<"&$H14)) | K14: =IF($D14="","",IFERROR(INDEX(Units_Owners!$H$5:$H$504,MATCH($D14,Units_Owners!$A$5:$A$504,0)),Setup!$B$10)) | L14: =IF($D14="","",Setup!$B$11) | M14: =IF($D14="","",IF(AND(TODAY()>=Setup!$B$9,$P14>0),Setup!$B$12,0)) | N14: =IF($D14="","",SUM($J14:$M14)) | O14: =IF($A14="","",SUMIFS(Payments!$F:$F,Payments!$D:$D,$A14)) | P14: =IF($D14="","",MAX(0,$N14-$O14)) | Q14: =IF($D14="","",IF(IFERROR(INDEX(Units_Owners!$I$5:$I$504,MATCH($D14,Units_Owners!$A$5:$A$504,0)),"No")<>"Yes","Skip - Inactive",IF($P14=0,"Paid",IF(TODAY()>$I14,"Past Due","Open"))))
A15: =IF($D15="","","INV-"&$B15&"-"&$C15&"-"&TEXT(ROW(A11),"0000")) | B15: =Setup!$B$5 | C15: =Setup!$B$6 | D15: =IFERROR(INDEX(Units_Owners!$A$5:$A$504,ROWS($A$5:A15)),"") | E15: =IF($D15="","",IFERROR(INDEX(Units_Owners!$B$5:$B$504,MATCH($D15,Units_Owners!$A$5:$A$504,0)),"")) | F15: =IF($D15="","",IFERROR(INDEX(Units_Owners!$C$5:$C$504,MATCH($D15,Units_Owners!$A$5:$A$504,0)),"")) | G15: =IF($D15="","",IFERROR(INDEX(Units_Owners!$D$5:$D$504,MATCH($D15,Units_Owners!$A$5:$A$504,0)),"")) | H15: =Setup!$B$7 | I15: =Setup!$B$8 | J15: =IF($D15="","",IFERROR(INDEX(Units_Owners!$J$5:$J$504,MATCH($D15,Units_Owners!$A$5:$A$504,0)),0)+SUMIFS(Ledger!$F:$F,Ledger!$B:$B,$D15,Ledger!$D:$D,"<"&$H15)-SUMIFS(Ledger!$G:$G,Ledger!$B:$B,$D15,Ledger!$D:$D,"<"&$H15)) | K15: =IF($D15="","",IFERROR(INDEX(Units_Owners!$H$5:$H$504,MATCH($D15,Units_Owners!$A$5:$A$504,0)),Setup!$B$10)) | L15: =IF($D15="","",Setup!$B$11) | M15: =IF($D15="","",IF(AND(TODAY()>=Setup!$B$9,$P15>0),Setup!$B$12,0)) | N15: =IF($D15="","",SUM($J15:$M15)) | O15: =IF($A15="","",SUMIFS(Payments!$F:$F,Payments!$D:$D,$A15)) | P15: =IF($D15="","",MAX(0,$N15-$O15)) | Q15: =IF($D15="","",IF(IFERROR(INDEX(Units_Owners!$I$5:$I$504,MATCH($D15,Units_Owners!$A$5:$A$504,0)),"No")<>"Yes","Skip - Inactive",IF($P15=0,"Paid",IF(TODAY()>$I15,"Past Due","Open"))))
A16: =IF($D16="","","INV-"&$B16&"-"&$C16&"-"&TEXT(ROW(A12),"0000")) | B16: =Setup!$B$5 | C16: =Setup!$B$6 | D16: =IFERROR(INDEX(Units_Owners!$A$5:$A$504,ROWS($A$5:A16)),"") | E16: =IF($D16="","",IFERROR(INDEX(Units_Owners!$B$5:$B$504,MATCH($D16,Units_Owners!$A$5:$A$504,0)),"")) | F16: =IF($D16="","",IFERROR(INDEX(Units_Owners!$C$5:$C$504,MATCH($D16,Units_Owners!$A$5:$A$504,0)),"")) | G16: =IF($D16="","",IFERROR(INDEX(Units_Owners!$D$5:$D$504,MATCH($D16,Units_Owners!$A$5:$A$504,0)),"")) | H16: =Setup!$B$7 | I16: =Setup!$B$8 | J16: =IF($D16="","",IFERROR(INDEX(Units_Owners!$J$5:$J$504,MATCH($D16,Units_Owners!$A$5:$A$504,0)),0)+SUMIFS(Ledger!$F:$F,Ledger!$B:$B,$D16,Ledger!$D:$D,"<"&$H16)-SUMIFS(Ledger!$G:$G,Ledger!$B:$B,$D16,Ledger!$D:$D,"<"&$H16)) | K16: =IF($D16="","",IFERROR(INDEX(Units_Owners!$H$5:$H$504,MATCH($D16,Units_Owners!$A$5:$A$504,0)),Setup!$B$10)) | L16: =IF($D16="","",Setup!$B$11) | M16: =IF($D16="","",IF(AND(TODAY()>=Setup!$B$9,$P16>0),Setup!$B$12,0)) | N16: =IF($D16="","",SUM($J16:$M16)) | O16: =IF($A16="","",SUMIFS(Payments!$F:$F,Payments!$D:$D,$A16)) | P16: =IF($D16="","",MAX(0,$N16-$O16)) | Q16: =IF($D16="","",IF(IFERROR(INDEX(Units_Owners!$I$5:$I$504,MATCH($D16,Units_Owners!$A$5:$A$504,0)),"No")<>"Yes","Skip - Inactive",IF($P16=0,"Paid",IF(TODAY()>$I16,"Past Due","Open"))))
... A504: =IF($D504="","","INV-"&$B504&"-"&$C504&"-"&TEXT(ROW(A500),"0000")) | B504: =Setup!$B$5 | C504: =Setup!$B$6 | D504: =IFERROR(INDEX(Units_Owners!$A$5:$A$504,ROWS($A$5:A504)),"") | E504: =IF($D504="","",IFERROR(INDEX(Units_Owners!$B$5:$B$504,MATCH($D504,Units_Owners!$A$5:$A$504,0)),"")) | F504: =IF($D504="","",IFERROR(INDEX(Units_Owners!$C$5:$C$504,MATCH($D504,Units_Owners!$A$5:$A$504,0)),"")) | G504: =IF($D504="","",IFERROR(INDEX(Units_Owners!$D$5:$D$504,MATCH($D504,Units_Owners!$A$5:$A$504,0)),"")) | H504: =Setup!$B$7 | I504: =Setup!$B$8 | J504: =IF($D504="","",IFERROR(INDEX(Units_Owners!$J$5:$J$504,MATCH($D504,Units_Owners!$A$5:$A$504,0)),0)+SUMIFS(Ledger!$F:$F,Ledger!$B:$B,$D504,Ledger!$D:$D,"<"&$H504)-SUMIFS(Ledger!$G:$G,Ledger!$B:$B,$D504,Ledger!$D:$D,"<"&$H504)) | K504: =IF($D504="","",IFERROR(INDEX(Units_Owners!$H$5:$H$504,MATCH($D504,Units_Owners!$A$5:$A$504,0)),Setup!$B$10)) | L504: =IF($D504="","",Setup!$B$11) | M504: =IF($D504="","",IF(AND(TODAY()>=Setup!$B$9,$P504>0),Setup!$B$12,0)) | N504: =IF($D504="","",SUM($J504:$M504)) | O504: =IF($A504="","",SUMIFS(Payments!$F:$F,Payments!$D:$D,$A504)) | P504: =IF($D504="","",MAX(0,$N504-$O504)) | Q504: =IF($D504="","",IF(IFERROR(INDEX(Units_Owners!$I$5:$I$504,MATCH($D504,Units_Owners!$A$5:$A$504,0)),"No")<>"Yes","Skip - Inactive",IF($P504=0,"Paid",IF(TODAY()>$I504,"Past Due","Open"))))

Sheet Payments
A1: Payments
A4: Payment ID | B4: Date Received | C4: Unit ID | D4: Invoice No. | E4: Owner Name | F4: Amount Paid | G4: Payment Method | H4: Reference No. | I4: Deposit Account | J4: Receipt Sent? | K4: Notes
E5: =IF($C5="","",IFERROR(INDEX(Units_Owners!$C$5:$C$504,MATCH($C5,Units_Owners!$A$5:$A$504,0)),""))
E6: =IF($C6="","",IFERROR(INDEX(Units_Owners!$C$5:$C$504,MATCH($C6,Units_Owners!$A$5:$A$504,0)),""))
E7: =IF($C7="","",IFERROR(INDEX(Units_Owners!$C$5:$C$504,MATCH($C7,Units_Owners!$A$5:$A$504,0)),""))
E8: =IF($C8="","",IFERROR(INDEX(Units_Owners!$C$5:$C$504,MATCH($C8,Units_Owners!$A$5:$A$504,0)),""))
E9: =IF($C9="","",IFERROR(INDEX(Units_Owners!$C$5:$C$504,MATCH($C9,Units_Owners!$A$5:$A$504,0)),""))
E10: =IF($C10="","",IFERROR(INDEX(Units_Owners!$C$5:$C$504,MATCH($C10,Units_Owners!$A$5:$A$504,0)),""))
E11: =IF($C11="","",IFERROR(INDEX(Units_Owners!$C$5:$C$504,MATCH($C11,Units_Owners!$A$5:$A$504,0)),""))
E12: =IF($C12="","",IFERROR(INDEX(Units_Owners!$C$5:$C$504,MATCH($C12,Units_Owners!$A$5:$A$504,0)),""))
E13: =IF($C13="","",IFERROR(INDEX(Units_Owners!$C$5:$C$504,MATCH($C13,Units_Owners!$A$5:$A$504,0)),""))
E14: =IF($C14="","",IFERROR(INDEX(Units_Owners!$C$5:$C$504,MATCH($C14,Units_Owners!$A$5:$A$504,0)),""))
E15: =IF($C15="","",IFERROR(INDEX(Units_Owners!$C$5:$C$504,MATCH($C15,Units_Owners!$A$5:$A$504,0)),""))
E16: =IF($C16="","",IFERROR(INDEX(Units_Owners!$C$5:$C$504,MATCH($C16,Units_Owners!$A$5:$A$504,0)),""))
... E504: =IF($C504="","",IFERROR(INDEX(Units_Owners!$C$5:$C$504,MATCH($C504,Units_Owners!$A$5:$A$504,0)),""))

Sheet Ledger
A1: Ledger
A4: Ledger ID | B4: Unit ID | C4: Invoice No. | D4: Transaction Date | E4: Type | F4: Debit | G4: Credit | H4: Balance | I4: Reference | J4: Notes
H5: =IF($B5="","",SUMIFS($F:$F,$B:$B,$B5,$D:$D,"<="&$D5)-SUMIFS($G:$G,$B:$B,$B5,$D:$D,"<="&$D5))
H6: =IF($B6="","",SUMIFS($F:$F,$B:$B,$B6,$D:$D,"<="&$D6)-SUMIFS($G:$G,$B:$B,$B6,$D:$D,"<="&$D6))
H7: =IF($B7="","",SUMIFS($F:$F,$B:$B,$B7,$D:$D,"<="&$D7)-SUMIFS($G:$G,$B:$B,$B7,$D:$D,"<="&$D7))
H8: =IF($B8="","",SUMIFS($F:$F,$B:$B,$B8,$D:$D,"<="&$D8)-SUMIFS($G:$G,$B:$B,$B8,$D:$D,"<="&$D8))
H9: =IF($B9="","",SUMIFS($F:$F,$B:$B,$B9,$D:$D,"<="&$D9)-SUMIFS($G:$G,$B:$B,$B9,$D:$D,"<="&$D9))
H10: =IF($B10="","",SUMIFS($F:$F,$B:$B,$B10,$D:$D,"<="&$D10)-SUMIFS($G:$G,$B:$B,$B10,$D:$D,"<="&$D10))
H11: =IF($B11="","",SUMIFS($F:$F,$B:$B,$B11,$D:$D,"<="&$D11)-SUMIFS($G:$G,$B:$B,$B11,$D:$D,"<="&$D11))
H12: =IF($B12="","",SUMIFS($F:$F,$B:$B,$B12,$D:$D,"<="&$D12)-SUMIFS($G:$G,$B:$B,$B12,$D:$D,"<="&$D12))
H13: =IF($B13="","",SUMIFS($F:$F,$B:$B,$B13,$D:$D,"<="&$D13)-SUMIFS($G:$G,$B:$B,$B13,$D:$D,"<="&$D13))
H14: =IF($B14="","",SUMIFS($F:$F,$B:$B,$B14,$D:$D,"<="&$D14)-SUMIFS($G:$G,$B:$B,$B14,$D:$D,"<="&$D14))
H15: =IF($B15="","",SUMIFS($F:$F,$B:$B,$B15,$D:$D,"<="&$D15)-SUMIFS($G:$G,$B:$B,$B15,$D:$D,"<="&$D15))
H16: =IF($B16="","",SUMIFS($F:$F,$B:$B,$B16,$D:$D,"<="&$D16)-SUMIFS($G:$G,$B:$B,$B16,$D:$D,"<="&$D16))
... H1004: =IF($B1004="","",SUMIFS($F:$F,$B:$B,$B1004,$D:$D,"<="&$D1004)-SUMIFS($G:$G,$B:$B,$B1004,$D:$D,"<="&$D1004))

Sheet Aging_Report
A1: Aging Report
A4: Unit ID | B4: Owner Name | C4: Invoice No. | D4: Due Date | E4: Balance Due | F4: Days Past Due | G4: Aging Bucket | H4: Status
A5: =Quarterly_Billing_Run!D5 | B5: =Quarterly_Billing_Run!F5 | C5: =Quarterly_Billing_Run!A5 | D5: =Quarterly_Billing_Run!I5 | E5: =Quarterly_Billing_Run!P5 | F5: =IF($E5=0,0,MAX(0,TODAY()-$D5)) | G5: =IF($E5=0,"Current",IF($F5<=30,"1-30",IF($F5<=60,"31-60",IF($F5<=90,"61-90","90+")))) | H5: =Quarterly_Billing_Run!Q5
A6: =Quarterly_Billing_Run!D6 | B6: =Quarterly_Billing_Run!F6 | C6: =Quarterly_Billing_Run!A6 | D6: =Quarterly_Billing_Run!I6 | E6: =Quarterly_Billing_Run!P6 | F6: =IF($E6=0,0,MAX(0,TODAY()-$D6)) | G6: =IF($E6=0,"Current",IF($F6<=30,"1-30",IF($F6<=60,"31-60",IF($F6<=90,"61-90","90+")))) | H6: =Quarterly_Billing_Run!Q6
A7: =Quarterly_Billing_Run!D7 | B7: =Quarterly_Billing_Run!F7 | C7: =Quarterly_Billing_Run!A7 | D7: =Quarterly_Billing_Run!I7 | E7: =Quarterly_Billing_Run!P7 | F7: =IF($E7=0,0,MAX(0,TODAY()-$D7)) | G7: =IF($E7=0,"Current",IF($F7<=30,"1-30",IF($F7<=60,"31-60",IF($F7<=90,"61-90","90+")))) | H7: =Quarterly_Billing_Run!Q7
A8: =Quarterly_Billing_Run!D8 | B8: =Quarterly_Billing_Run!F8 | C8: =Quarterly_Billing_Run!A8 | D8: =Quarterly_Billing_Run!I8 | E8: =Quarterly_Billing_Run!P8 | F8: =IF($E8=0,0,MAX(0,TODAY()-$D8)) | G8: =IF($E8=0,"Current",IF($F8<=30,"1-30",IF($F8<=60,"31-60",IF($F8<=90,"61-90","90+")))) | H8: =Quarterly_Billing_Run!Q8
A9: =Quarterly_Billing_Run!D9 | B9: =Quarterly_Billing_Run!F9 | C9: =Quarterly_Billing_Run!A9 | D9: =Quarterly_Billing_Run!I9 | E9: =Quarterly_Billing_Run!P9 | F9: =IF($E9=0,0,MAX(0,TODAY()-$D9)) | G9: =IF($E9=0,"Current",IF($F9<=30,"1-30",IF($F9<=60,"31-60",IF($F9<=90,"61-90","90+")))) | H9: =Quarterly_Billing_Run!Q9
A10: =Quarterly_Billing_Run!D10 | B10: =Quarterly_Billing_Run!F10 | C10: =Quarterly_Billing_Run!A10 | D10: =Quarterly_Billing_Run!I10 | E10: =Quarterly_Billing_Run!P10 | F10: =IF($E10=0,0,MAX(0,TODAY()-$D10)) | G10: =IF($E10=0,"Current",IF($F10<=30,"1-30",IF($F10<=60,"31-60",IF($F10<=90,"61-90","90+")))) | H10: =Quarterly_Billing_Run!Q10
A11: =Quarterly_Billing_Run!D11 | B11: =Quarterly_Billing_Run!F11 | C11: =Quarterly_Billing_Run!A11 | D11: =Quarterly_Billing_Run!I11 | E11: =Quarterly_Billing_Run!P11 | F11: =IF($E11=0,0,MAX(0,TODAY()-$D11)) | G11: =IF($E11=0,"Current",IF($F11<=30,"1-30",IF($F11<=60,"31-60",IF($F11<=90,"61-90","90+")))) | H11: =Quarterly_Billing_Run!Q11
A12: =Quarterly_Billing_Run!D12 | B12: =Quarterly_Billing_Run!F12 | C12: =Quarterly_Billing_Run!A12 | D12: =Quarterly_Billing_Run!I12 | E12: =Quarterly_Billing_Run!P12 | F12: =IF($E12=0,0,MAX(0,TODAY()-$D12)) | G12: =IF($E12=0,"Current",IF($F12<=30,"1-30",IF($F12<=60,"31-60",IF($F12<=90,"61-90","90+")))) | H12: =Quarterly_Billing_Run!Q12
A13: =Quarterly_Billing_Run!D13 | B13: =Quarterly_Billing_Run!F13 | C13: =Quarterly_Billing_Run!A13 | D13: =Quarterly_Billing_Run!I13 | E13: =Quarterly_Billing_Run!P13 | F13: =IF($E13=0,0,MAX(0,TODAY()-$D13)) | G13: =IF($E13=0,"Current",IF($F13<=30,"1-30",IF($F13<=60,"31-60",IF($F13<=90,"61-90","90+")))) | H13: =Quarterly_Billing_Run!Q13
A14: =Quarterly_Billing_Run!D14 | B14: =Quarterly_Billing_Run!F14 | C14: =Quarterly_Billing_Run!A14 | D14: =Quarterly_Billing_Run!I14 | E14: =Quarterly_Billing_Run!P14 | F14: =IF($E14=0,0,MAX(0,TODAY()-$D14)) | G14: =IF($E14=0,"Current",IF($F14<=30,"1-30",IF($F14<=60,"31-60",IF($F14<=90,"61-90","90+")))) | H14: =Quarterly_Billing_Run!Q14
A15: =Quarterly_Billing_Run!D15 | B15: =Quarterly_Billing_Run!F15 | C15: =Quarterly_Billing_Run!A15 | D15: =Quarterly_Billing_Run!I15 | E15: =Quarterly_Billing_Run!P15 | F15: =IF($E15=0,0,MAX(0,TODAY()-$D15)) | G15: =IF($E15=0,"Current",IF($F15<=30,"1-30",IF($F15<=60,"31-60",IF($F15<=90,"61-90","90+")))) | H15: =Quarterly_Billing_Run!Q15
A16: =Quarterly_Billing_Run!D16 | B16: =Quarterly_Billing_Run!F16 | C16: =Quarterly_Billing_Run!A16 | D16: =Quarterly_Billing_Run!I16 | E16: =Quarterly_Billing_Run!P16 | F16: =IF($E16=0,0,MAX(0,TODAY()-$D16)) | G16: =IF($E16=0,"Current",IF($F16<=30,"1-30",IF($F16<=60,"31-60",IF($F16<=90,"61-90","90+")))) | H16: =Quarterly_Billing_Run!Q16
... A504: =Quarterly_Billing_Run!D504 | B504: =Quarterly_Billing_Run!F504 | C504: =Quarterly_Billing_Run!A504 | D504: =Quarterly_Billing_Run!I504 | E504: =Quarterly_Billing_Run!P504 | F504: =IF($E504=0,0,MAX(0,TODAY()-$D504)) | G504: =IF($E504=0,"Current",IF($F504<=30,"1-30",IF($F504<=60,"31-60",IF($F504<=90,"61-90","90+")))) | H504: =Quarterly_Billing_Run!Q504

Sheet Invoice_Template
A1: Invoice Template
A3: Invoice No. | B3: INV-2026-Q1-0001
A5: =Setup!$B$4
A7: Owner | B7: =IFERROR(INDEX(Quarterly_Billing_Run!$F:$F,MATCH($B$3,Quarterly_Billing_Run!$A:$A,0)),"")
A8: Unit | B8: =IFERROR(INDEX(Quarterly_Billing_Run!$E:$E,MATCH($B$3,Quarterly_Billing_Run!$A:$A,0)),"")
A9: Email | B9: =IFERROR(INDEX(Quarterly_Billing_Run!$G:$G,MATCH($B$3,Quarterly_Billing_Run!$A:$A,0)),"")
A10: Billing Year | B10: =IFERROR(INDEX(Quarterly_Billing_Run!$B:$B,MATCH($B$3,Quarterly_Billing_Run!$A:$A,0)),"")
A11: Quarter | B11: =IFERROR(INDEX(Quarterly_Billing_Run!$C:$C,MATCH($B$3,Quarterly_Billing_Run!$A:$A,0)),"")
A12: Charge Date | B12: =IFERROR(INDEX(Quarterly_Billing_Run!$H:$H,MATCH($B$3,Quarterly_Billing_Run!$A:$A,0)),"")
A13: Due Date | B13: =IFERROR(INDEX(Quarterly_Billing_Run!$I:$I,MATCH($B$3,Quarterly_Billing_Run!$A:$A,0)),"")
A16: Description | B16: Amount
A17: Prior Balance | B17: =IFERROR(INDEX(Quarterly_Billing_Run!$J:$J,MATCH($B$3,Quarterly_Billing_Run!$A:$A,0)),0)
A18: Quarterly Dues | B18: =IFERROR(INDEX(Quarterly_Billing_Run!$K:$K,MATCH($B$3,Quarterly_Billing_Run!$A:$A,0)),0)
A19: Special Assessment | B19: =IFERROR(INDEX(Quarterly_Billing_Run!$L:$L,MATCH($B$3,Quarterly_Billing_Run!$A:$A,0)),0)
A20: Late Fee | B20: =IFERROR(INDEX(Quarterly_Billing_Run!$M:$M,MATCH($B$3,Quarterly_Billing_Run!$A:$A,0)),0)
A21: Payments Applied | B21: =-IFERROR(INDEX(Quarterly_Billing_Run!$O:$O,MATCH($B$3,Quarterly_Billing_Run!$A:$A,0)),0)
A22: Balance Due | B22: =IFERROR(INDEX(Quarterly_Billing_Run!$P:$P,MATCH($B$3,Quarterly_Billing_Run!$A:$A,0)),0)
A24: Payment Instructions
A25: =Setup!$B$13
A27: Invoice Memo
A28: =Setup!$B$14

Sheet Owner_Statement
A1: Owner Statement
A3: Unit ID | B3: U-001
A5: Owner | B5: =IFERROR(INDEX(Units_Owners!$C:$C,MATCH($B$3,Units_Owners!$A:$A,0)),"")
A8: Date | B8: Type | C8: Invoice No. | D8: Debit | E8: Credit | F8: Balance | G8: Notes
A10: Use Ledger filters by Unit ID for detailed statement history, or add a macro to populate this section automatically.

Sheet Print_Email_Log
A1: Print and Email Log
A4: Invoice No. | B4: Unit ID | C4: Owner Name | D4: Delivery Method | E4: Delivery Status | F4: Sent/Printed Date | G4: File Name or Email Reference | H4: Notes

Sheet Macro_Blueprint
A1: Macro Blueprint for Future .xlsm Version
A4: Button / Macro | B4: Purpose | C4: Recommended Behavior
A5: Generate Quarterly Billing | B5: Create a clean billing run for the selected quarter. | C5: Clear prior draft rows after confirmation, loop through active Units_Owners rows, assign invoice numbers, copy dues/special assessment, calculate prior balance, and set status to Draft/Open.
A6: Export Invoices to PDF | B6: Save one PDF per invoice from Invoice_Template. | C6: Loop through Quarterly_Billing_Run rows where status is Open or Sent, place invoice number into Invoice_Template!B3, export print area to PDF using file names like 2026_Q1_Unit_101_Owner.pdf.
A7: Mark Billing Run as Sent | B7: Lock in the send/print step. | C7: Update Sent Date, status, and Print_Email_Log for all selected invoices; optionally prevent duplicate send without confirmation.
A8: Apply Late Fees | B8: Add approved late fees after due date. | C8: For invoices still open after Setup!Late Fee Date, add the configured late fee once, update balance/status, and add a ledger row.
A9: Generate Owner Statements | B9: Create statements by unit for owners with open balances. | C9: Filter Ledger by Unit ID, populate Owner_Statement, export or print statements for delinquency review.
A12: Note | B12: After you approve this workbook layout, the next step is to convert it to .xlsm and add these macros as real Excel buttons.
